namae/__init__.py
namae/go.py
namae-0.1.dist-info/DESCRIPTION.rst
namae-0.1.dist-info/entry_points.txt
namae-0.1.dist-info/METADATA
namae-0.1.dist-info/metadata.json
namae-0.1.dist-info/RECORD
namae-0.1.dist-info/top_level.txt
namae-0.1.dist-info/WHEEL
