Metadata-Version: 2.0
Name: namae
Version: 0.1
Summary: naming
Home-page: https://github.com/podhmo/namae
Author: podhmo
Author-email: ababjam61@gmail.com
License: UNKNOWN
Keywords: naming,string,kebab-case,camelCase,snakeCase
Platform: UNKNOWN
Classifier: Programming Language :: Python
Classifier: Programming Language :: Python :: Implementation :: CPython
Provides-Extra: docs
Provides-Extra: testing
